pycache_wipe/__init__.py
pycache_wipe/main.py
pycache_wipe-1.0.0.dist-info/METADATA
pycache_wipe-1.0.0.dist-info/WHEEL
pycache_wipe-1.0.0.dist-info/entry_points.txt
pycache_wipe-1.0.0.dist-info/top_level.txt
pycache_wipe-1.0.0.dist-info/RECORD
