Metadata-Version: 2.2
Name: pycache-wipe
Version: 1.0.0
Summary: Simple utility to delete __pycache__ folders.
Author-email: Gabriel Stanier <support@datadude.dev>
License: MIT
